Metadata-Version: 1.2
Name: file8601
Version: 0.0.4
Summary: A library for working with ISO 8601 in file names.
Home-page: https://gitlab.com/brian_pond/file8601
Author: Brian Pond
Author-email: brian@pondconsulting.net
License: MIT
Keywords: datetime
Platform: Linux
Classifier: Development Status :: 3 - Alpha
Classifier: Intended Audience :: Developers
Classifier: License :: OSI Approved :: MIT License
Classifier: Operating System :: POSIX :: Linux
Classifier: Programming Language :: Python
Classifier: Programming Language :: Python :: 3.7
Classifier: Topic :: Software Development :: Libraries :: Python Modules
Classifier: Topic :: System :: Archiving :: Backup
Requires-Python: >=3.7
